{
  "total_global_paginas": 7360,
  "total_global_processos": 300155,
  "ritmo_sessao": {
    "5min": {
      "novas_paginas": 103,
      "media_pag_min": 20.6,
      "novos_processos": 1255,
      "media_proc_min": 251.0
    },
    "30min": {
      "novas_paginas": 501,
      "media_pag_min": 16.7,
      "novos_processos": 5216,
      "media_proc_min": 173.87
    },
    "180min": {
      "novas_paginas": 3221,
      "media_pag_min": 17.89,
      "novos_processos": 34679,
      "media_proc_min": 192.66
    }
  },
  "timestamp_atualizacao": "2026-01-17T10:53:22.849538"
}