{
  "total_global_paginas": 9259,
  "total_global_processos": 352976,
  "ritmo_sessao": {
    "5min": {
      "novas_paginas": 172,
      "media_pag_min": 34.4,
      "novos_processos": 614,
      "media_proc_min": 122.8
    },
    "30min": {
      "novas_paginas": 959,
      "media_pag_min": 31.97,
      "novos_processos": 2277,
      "media_proc_min": 75.9
    },
    "180min": {
      "novas_paginas": 4396,
      "media_pag_min": 24.42,
      "novos_processos": 10069,
      "media_proc_min": 55.94
    }
  },
  "timestamp_atualizacao": "2026-01-18T03:26:15.406460"
}